ogdf_python_widget/__init__.py
ogdf_python_widget/_version.py
ogdf_python_widget/basicGraphRepresentation.html
ogdf_python_widget/pythonize.py
ogdf_python_widget/widget.py
ogdf_python_widget-0.1.1.data/data/share/jupyter/labextensions/ogdf-python-widget/package.json
ogdf_python_widget-0.1.1.data/data/share/jupyter/labextensions/ogdf-python-widget/static/261.3a381882b3e06255f9ae.js
ogdf_python_widget-0.1.1.data/data/share/jupyter/labextensions/ogdf-python-widget/static/486.51b3ec9296b3c8767ad3.js
ogdf_python_widget-0.1.1.data/data/share/jupyter/labextensions/ogdf-python-widget/static/486.51b3ec9296b3c8767ad3.js.LICENSE.txt
ogdf_python_widget-0.1.1.data/data/share/jupyter/labextensions/ogdf-python-widget/static/568.9bf712948624684697ef.js
ogdf_python_widget-0.1.1.data/data/share/jupyter/labextensions/ogdf-python-widget/static/829.0e90c8d64eaa4eca9044.js
ogdf_python_widget-0.1.1.data/data/share/jupyter/labextensions/ogdf-python-widget/static/remoteEntry.515f28d56250bea52516.js
ogdf_python_widget-0.1.1.data/data/share/jupyter/labextensions/ogdf-python-widget/static/style.js
ogdf_python_widget-0.1.1.data/data/share/jupyter/labextensions/ogdf-python-widget/static/third-party-licenses.json
ogdf_python_widget-0.1.1.data/data/share/jupyter/nbextensions/ogdf-python-widget/extension.js
ogdf_python_widget-0.1.1.data/data/share/jupyter/nbextensions/ogdf-python-widget/index.js
ogdf_python_widget-0.1.1.data/data/share/jupyter/nbextensions/ogdf-python-widget/index.js.LICENSE.txt
ogdf_python_widget-0.1.1.data/data/etc/jupyter/nbconfig/notebook.d/ogdf-python-widget.json
ogdf_python_widget-0.1.1.data/data/share/jupyter/labextensions/ogdf-python-widget/install.json
ogdf_python_widget-0.1.1.dist-info/METADATA
ogdf_python_widget-0.1.1.dist-info/WHEEL
ogdf_python_widget-0.1.1.dist-info/RECORD
