Metadata-Version: 2.1
Name: ogdf-python-widget
Version: 0.1.1
Summary: A Custom Jupyter Widget Library
Author-email: Andreas Strobl <strobland@fim.uni-passau.de>, "Simon D. Fink" <finksim@fim.uni-passau.de>
Keywords: algorithm,drawing,graph,ipython,jupyter,network,ogdf,widgets
Classifier: Development Status :: 4 - Beta
Classifier: Framework :: IPython
Classifier: Intended Audience :: Developers
Classifier: Intended Audience :: Science/Research
Classifier: Programming Language :: Python :: 3.6
Classifier: Programming Language :: Python :: 3.7
Classifier: Programming Language :: Python :: 3.8
Classifier: Programming Language :: Python :: 3.9
Classifier: Topic :: Multimedia :: Graphics
Requires-Dist: importlib-resources
Requires-Dist: ipywidgets<8,>=7
Requires-Dist: ogdf-python
